mmdeploy/__init__.py
mmdeploy/version.py
mmdeploy/apis/__init__.py
mmdeploy/apis/calibration.py
mmdeploy/apis/extract_model.py
mmdeploy/apis/inference.py
mmdeploy/apis/pytorch2onnx.py
mmdeploy/apis/pytorch2torchscript.py
mmdeploy/apis/visualize.py
mmdeploy/apis/ascend/__init__.py
mmdeploy/apis/core/__init__.py
mmdeploy/apis/core/pipeline_manager.py
mmdeploy/apis/coreml/__init__.py
mmdeploy/apis/ncnn/__init__.py
mmdeploy/apis/onnx/__init__.py
mmdeploy/apis/onnx/export.py
mmdeploy/apis/onnx/optimizer.py
mmdeploy/apis/onnx/partition.py
mmdeploy/apis/onnx/passes/__init__.py
mmdeploy/apis/onnx/passes/optimize_onnx.py
mmdeploy/apis/onnxruntime/__init__.py
mmdeploy/apis/openvino/__init__.py
mmdeploy/apis/openvino/utils.py
mmdeploy/apis/pplnn/__init__.py
mmdeploy/apis/rknn/__init__.py
mmdeploy/apis/sdk/__init__.py
mmdeploy/apis/snpe/__init__.py
mmdeploy/apis/tensorrt/__init__.py
mmdeploy/apis/torch_jit/__init__.py
mmdeploy/apis/torch_jit/trace.py
mmdeploy/apis/tvm/__init__.py
mmdeploy/apis/utils/__init__.py
mmdeploy/apis/utils/calibration.py
mmdeploy/apis/utils/utils.py
mmdeploy/apis/vacc/__init__.py
mmdeploy/backend/__init__.py
mmdeploy/backend/ascend/__init__.py
mmdeploy/backend/ascend/backend_manager.py
mmdeploy/backend/ascend/onnx2ascend.py
mmdeploy/backend/ascend/utils.py
mmdeploy/backend/ascend/wrapper.py
mmdeploy/backend/base/__init__.py
mmdeploy/backend/base/backend_manager.py
mmdeploy/backend/base/backend_wrapper_registry.py
mmdeploy/backend/base/base_wrapper.py
mmdeploy/backend/coreml/__init__.py
mmdeploy/backend/coreml/backend_manager.py
mmdeploy/backend/coreml/ops.py
mmdeploy/backend/coreml/torchscript2coreml.py
mmdeploy/backend/coreml/wrapper.py
mmdeploy/backend/ncnn/__init__.py
mmdeploy/backend/ncnn/backend_manager.py
mmdeploy/backend/ncnn/init_plugins.py
mmdeploy/backend/ncnn/onnx2ncnn.py
mmdeploy/backend/ncnn/quant.py
mmdeploy/backend/ncnn/wrapper.py
mmdeploy/backend/onnxruntime/__init__.py
mmdeploy/backend/onnxruntime/backend_manager.py
mmdeploy_vitrox-1.3.1.dist-info/LICENSE
mmdeploy_vitrox-1.3.1.dist-info/METADATA
mmdeploy_vitrox-1.3.1.dist-info/WHEEL
mmdeploy_vitrox-1.3.1.dist-info/top_level.txt
mmdeploy_vitrox-1.3.1.dist-info/RECORD
